setup.py
fiveruns/__init__.py
fiveruns.dash.django.egg-info/PKG-INFO
fiveruns.dash.django.egg-info/SOURCES.txt
fiveruns.dash.django.egg-info/dependency_links.txt
fiveruns.dash.django.egg-info/namespace_packages.txt
fiveruns.dash.django.egg-info/requires.txt
fiveruns.dash.django.egg-info/top_level.txt
fiveruns/dash/__init__.py
fiveruns/dash/django/__init__.py
fiveruns/dash/django/startup.py
fiveruns/dash/django/version.py