Metadata-Version: 1.0
Name: fiveruns.dash.django
Version: 0.2.1
Summary: FiveRuns Dash recipe for Django, packaged as an Django App
Home-page: http://dash.fiveruns.com
Author: FiveRuns Development Team
Author-email: dev@fiveruns.com
License: MIT
Keywords: monitoring performance production metrics logging django
Platform: UNKNOWN
